tfm_client/__init__.py
tfm_client/client.py
tfm_client-0.0.3.dist-info/METADATA
tfm_client-0.0.3.dist-info/WHEEL
tfm_client-0.0.3.dist-info/top_level.txt
tfm_client-0.0.3.dist-info/RECORD
