Metadata-Version: 2.1
Name: tfm-client
Version: 0.0.3
Summary: UNKNOWN
Home-page: https://github.com/almenjonatan/tfm_api_client
Author: Jonatan Almen
Author-email: almen.jonatan@gmail.com
License: UNKNOWN
Platform: UNKNOWN
Classifier: Programming Language :: Python :: 3
Classifier: License :: OSI Approved :: MIT License
Classifier: Operating System :: OS Independent
Requires-Python: >=3.8
